lab1/collatz.sv
module collatz( input logic         clk,   // Clock
		input logic 	    go,    // Load value from n; start iterating
		input logic  [31:0] n,     // Start value; only read when go = 1
		output logic [31:0] dout,  // Iteration value: true after go = 1
		output logic 	    done); // True when dout reaches 1

   /* Replace this comment and the code below with your solution */
	assign done = (!go && (dout == 32'd1));

	/* triggered by rising edge */
	always_ff @(posedge clk) begin
		// Reset the state and start the computation.
		if (go) begin
			if(n==0)
				dout <= 32'd1;
			else
				dout <= n;
		end
		// core logic of Collatz conjecture.
		else if (!done) begin
			if (dout[0] == 1'b0) begin
				dout <= dout >> 1;
			end else begin
				dout <= (dout * 3) + 1;
			end
		end
	end
   /* Replace this comment and the code above with your solution */

endmodule

lab1/range.sv
module range
   #(parameter
     RAM_WORDS = 16,            // Number of counts to store in RAM
     RAM_ADDR_BITS = 4)         // Number of RAM address bits
   (input logic         clk,    // Clock
    input logic 	go,     // Read start and start testing
    input logic [31:0] 	start,  // Number to start from or count to read
    output logic 	done,   // True once memory is filled
    output logic [15:0] count); // Iteration count once finished

   logic 		cgo;    // "go" for the Collatz iterator
   logic                cdone;  // "done" from the Collatz iterator
   logic [31:0] 	n;      // number to start the Collatz iterator
   //logic [31:0] collatz_dout;

// verilator lint_off PINCONNECTEMPTY

   // Instantiate the Collatz iterator
   collatz c1(.clk(clk),
	      .go(cgo),
	      .n(n),
         .done(cdone),
	      .dout());

   logic [RAM_ADDR_BITS - 1:0] 	 num;         // The RAM address to write
   logic 			 running = 0; // True during the iterations

   /* Replace this comment and the code below with your solution,
      which should generate running, done, cgo, n, num, we, and din */
   // assign done = cdone;
   // assign cgo = go;
   // assign n = start;
   // assign din = 16'h0;
   // assign we = running;
   /* Replace this comment and the code above with your solution */

   logic 			 we=0;                    // Write din to addr
   logic [15:0] 		 din=10;                   // Data to write
   logic [15:0] 		 mem[RAM_WORDS - 1:0];  // The RAM itself
   logic [RAM_ADDR_BITS - 1:0] 	 addr;                  // Address to read/write
   logic go_last;       // cgo capture the rising edge of go and cdone.
   logic cdone_last;    // we capture the rising edge of cdone.

   logic [15:0] mem_tmp;

   assign addr = we ? num : start[RAM_ADDR_BITS-1:0];

   always_ff @(posedge clk) begin
      if (we) begin
         mem[addr] <= din;
         we <= 0;
      end

      if (done)
         mem_tmp <= mem[addr];
      count <= mem_tmp;

      if (go) begin
         running <= 1;
         n <= start;
         num <= 0;
         din <= 1;
         if (!go_last) cgo <= 1;
         else cgo <= 0;
         go_last <= go;
      end

      if (running) begin  // running is constanly treu during iterations
         if (!cgo && !cdone) begin
         /* check if callatz is not active or its not done yet. */
              din <= din + 1;
          end

         if (cdone) begin
            /* cdone is set, we is pulsed high to write din in RAM. */
            if (!cdone_last) begin
               cgo <= 1;
               we <= 1;
            end
            else begin
               cgo <= 0;
               we <= 1;
            end
            cdone_last <= cdone;

            din <= 1;
            num <= num+1; // num serves as the address pointer?
            n <= n+1;
            cdone <= 0;
            // when to stop?
            if (num == RAM_WORDS[RAM_ADDR_BITS-1:0]-1) begin
               running <= 0;
               done <= 1;  // if num reaches limit, done is set, we are all good.
            end
         end

      end
   end

endmodule

lab1/range.vcd
$version Generated by VerilatedVcd $end
$timescale 1ps $end

 $scope module TOP $end
  $var wire  1 > clk $end
  $var wire 16 B count [15:0] $end
  $var wire  1 A done $end
  $var wire  1 ? go $end
  $var wire 32 @ start [31:0] $end
  $scope module range $end
   $var wire 32 E RAM_ADDR_BITS [31:0] $end
   $var wire 32 D RAM_WORDS [31:0] $end
   $var wire  4 C addr [3:0] $end
   $var wire  1 $ cdone $end
   $var wire  1 ; cdone_last $end
   $var wire  1 # cgo $end
   $var wire  1 > clk $end
   $var wire 16 B count [15:0] $end
   $var wire 16 ) din [15:0] $end
   $var wire  1 A done $end
   $var wire  1 ? go $end
   $var wire  1 : go_last $end
   $var wire 16 * mem[0] [15:0] $end
   $var wire 16 4 mem[10] [15:0] $end
   $var wire 16 5 mem[11] [15:0] $end
   $var wire 16 6 mem[12] [15:0] $end
   $var wire 16 7 mem[13] [15:0] $end
   $var wire 16 8 mem[14] [15:0] $end
   $var wire 16 9 mem[15] [15:0] $end
   $var wire 16 + mem[1] [15:0] $end
   $var wire 16 , mem[2] [15:0] $end
   $var wire 16 - mem[3] [15:0] $end
   $var wire 16 . mem[4] [15:0] $end
   $var wire 16 / mem[5] [15:0] $end
   $var wire 16 0 mem[6] [15:0] $end
   $var wire 16 1 mem[7] [15:0] $end
   $var wire 16 2 mem[8] [15:0] $end
   $var wire 16 3 mem[9] [15:0] $end
   $var wire 16 < mem_tmp [15:0] $end
   $var wire 32 % n [31:0] $end
   $var wire  4 & num [3:0] $end
   $var wire  1 ' running $end
   $var wire 32 @ start [31:0] $end
   $var wire  1 ( we $end
   $scope module c1 $end
    $var wire  1 > clk $end
    $var wire  1 $ done $end
    $var wire 32 = dout [31:0] $end
    $var wire  1 # go $end
    $var wire 32 % n [31:0] $end
   $upscope $end
  $upscope $end
 $upscope $end
$enddefinitions $end


#0
0#
0$
b00000000000000000000000000000000 %
b0000 &
0'
0(
b0000000000001010 )
b0000000000000000 *
b0000000000000000 +
b0000000000000000 ,
b0000000000000000 -
b0000000000000000 .
b0000000000000000 /
b0000000000000000 0
b0000000000000000 1
b0000000000000000 2
b0000000000000000 3
b0000000000000000 4
b0000000000000000 5
b0000000000000000 6
b0000000000000000 7
b0000000000000000 8
b0000000000000000 9
0:
0;
b0000000000000000 <
b00000000000000000000000000000000 =
0>
1?
b00000000000000000000000000000111 @
0A
b0000000000000000 B
b0111 C
b00000000000000000000000000010000 D
b00000000000000000000000000000100 E
#10
1#
b00000000000000000000000000000111 %
1'
b0000000000000001 )
1:
1>
#20
0>
#30
0#
b00000000000000000000000000000111 =
1>
#40
0>
0?
#50
b0000000000000010 )
b00000000000000000000000000010110 =
1>
#60
0>
#70
b0000000000000011 )
b00000000000000000000000000001011 =
1>
#80
0>
#90
b0000000000000100 )
b00000000000000000000000000100010 =
1>
#100
0>
#110
b0000000000000101 )
b00000000000000000000000000010001 =
1>
#120
0>
#130
b0000000000000110 )
b00000000000000000000000000110100 =
1>
#140
0>
#150
b0000000000000111 )
b00000000000000000000000000011010 =
1>
#160
0>
#170
b0000000000001000 )
b00000000000000000000000000001101 =
1>
#180
0>
#190
b0000000000001001 )
b00000000000000000000000000101000 =
1>
#200
0>
#210
b0000000000001010 )
b00000000000000000000000000010100 =
1>
#220
0>
#230
b0000000000001011 )
b00000000000000000000000000001010 =
1>
#240
0>
#250
b0000000000001100 )
b00000000000000000000000000000101 =
1>
#260
0>
#270
b0000000000001101 )
b00000000000000000000000000010000 =
1>
#280
0>
#290
b0000000000001110 )
b00000000000000000000000000001000 =
1>
#300
0>
#310
b0000000000001111 )
b00000000000000000000000000000100 =
1>
#320
0>
#330
b0000000000010000 )
b00000000000000000000000000000010 =
1>
#340
0>
#350
b0000000000010001 )
b00000000000000000000000000000001 =
1>
#360
0>
#370
1$
b0000000000010010 )
1>
#380
0>
#390
1#
0$
b00000000000000000000000000001000 %
b0001 &
1(
b0000000000000001 )
1;
1>
b0001 C
#400
0>
#410
1$
0(
b0000000000000001 +
b00000000000000000000000000001000 =
1>
b0111 C
#420
0>
#430
0#
0$
b00000000000000000000000000001001 %
b0010 &
1(
1>
b0010 C
#440
0>
#450
0(
b0000000000000010 )
b0000000000000001 ,
b00000000000000000000000000000100 =
1>
b0111 C
#460
0>
#470
b0000000000000011 )
b00000000000000000000000000000010 =
1>
#480
0>
#490
b0000000000000100 )
b00000000000000000000000000000001 =
1>
#500
0>
#510
1$
b0000000000000101 )
1>
#520
0>
#530
0$
b00000000000000000000000000001010 %
b0011 &
1(
b0000000000000001 )
1>
b0011 C
#540
0>
#550
1$
0(
b0000000000000010 )
b0000000000000001 -
1>
b0111 C
#560
0>
#570
0$
b00000000000000000000000000001011 %
b0100 &
1(
b0000000000000001 )
1>
b0100 C
#580
0>
#590
1$
0(
b0000000000000010 )
b0000000000000001 .
1>
b0111 C
#600
0>
#610
0$
b00000000000000000000000000001100 %
b0101 &
1(
b0000000000000001 )
1>
b0101 C
#620
0>
#630
1$
0(
b0000000000000010 )
b0000000000000001 /
1>
b0111 C
#640
0>
#650
0$
b00000000000000000000000000001101 %
b0110 &
1(
b0000000000000001 )
1>
b0110 C
#660
0>
#670
1$
0(
b0000000000000010 )
b0000000000000001 0
1>
b0111 C
#680
0>
#690
0$
b00000000000000000000000000001110 %
b0111 &
1(
b0000000000000001 )
1>
#700
0>
#710
1$
0(
b0000000000000010 )
b0000000000000001 1
1>
#720
0>
#730
0$
b00000000000000000000000000001111 %
b1000 &
1(
b0000000000000001 )
1>
b1000 C
#740
0>
#750
1$
0(
b0000000000000010 )
b0000000000000001 2
1>
b0111 C
#760
0>
#770
0$
b00000000000000000000000000010000 %
b1001 &
1(
b0000000000000001 )
1>
b1001 C
#780
0>
#790
1$
0(
b0000000000000010 )
b0000000000000001 3
1>
b0111 C
#800
0>
#810
0$
b00000000000000000000000000010001 %
b1010 &
1(
b0000000000000001 )
1>
b1010 C
#820
0>
#830
1$
0(
b0000000000000010 )
b0000000000000001 4
1>
b0111 C
#840
0>
#850
0$
b00000000000000000000000000010010 %
b1011 &
1(
b0000000000000001 )
1>
b1011 C
#860
0>
#870
1$
0(
b0000000000000010 )
b0000000000000001 5
1>
b0111 C
#880
0>
#890
0$
b00000000000000000000000000010011 %
b1100 &
1(
b0000000000000001 )
1>
b1100 C
#900
0>
#910
1$
0(
b0000000000000010 )
b0000000000000001 6
1>
b0111 C
#920
0>
#930
0$
b00000000000000000000000000010100 %
b1101 &
1(
b0000000000000001 )
1>
b1101 C
#940
0>
#950
1$
0(
b0000000000000010 )
b0000000000000001 7
1>
b0111 C
#960
0>
#970
0$
b00000000000000000000000000010101 %
b1110 &
1(
b0000000000000001 )
1>
b1110 C
#980
0>
#990
1$
0(
b0000000000000010 )
b0000000000000001 8
1>
b0111 C
#1000
0>
#1010
0$
b00000000000000000000000000010110 %
b1111 &
1(
b0000000000000001 )
1>
b1111 C
#1020
0>
#1030
1$
0(
b0000000000000010 )
b0000000000000001 9
1>
b0111 C
#1040
0>
#1050
0$
b00000000000000000000000000010111 %
b0000 &
1(
b0000000000000001 )
1>
b0000 C
#1060
0>
#1070
1$
0(
b0000000000000010 )
b0000000000000001 *
1>
b0111 C
#1080
0>
#1090
0$
b00000000000000000000000000011000 %
b0001 &
1(
b0000000000000001 )
1>
b0001 C
#1100
0>
#1110
1$
0(
b0000000000000010 )
1>
b0111 C
#1120
0>
#1130
0$
b00000000000000000000000000011001 %
b0010 &
1(
b0000000000000001 )
1>
b0010 C
#1140
0>
#1150
1$
0(
b0000000000000010 )
1>
b0111 C
#1160
0>
#1170
0$
b00000000000000000000000000011010 %
b0011 &
1(
b0000000000000001 )
1>
b0011 C
#1180
0>
#1190
1$
0(
b0000000000000010 )
1>
b0111 C
#1200
0>
#1210
0$
b00000000000000000000000000011011 %
b0100 &
1(
b0000000000000001 )
1>
b0100 C
#1220
0>
#1230
1$
0(
b0000000000000010 )
1>
b0111 C
#1240
0>
#1250
0$
b00000000000000000000000000011100 %
b0101 &
1(
b0000000000000001 )
1>
b0101 C
#1260
0>
#1270
1$
0(
b0000000000000010 )
1>
b0111 C
#1280
0>
#1290
0$
b00000000000000000000000000011101 %
b0110 &
1(
b0000000000000001 )
1>
b0110 C
#1300
0>
#1310
1$
0(
b0000000000000010 )
1>
b0111 C
#1320
0>
#1330
0$
b00000000000000000000000000011110 %
b0111 &
1(
b0000000000000001 )
1>
#1340
0>
#1350
1$
0(
b0000000000000010 )
1>
#1360
0>
#1370
0$
b00000000000000000000000000011111 %
b1000 &
1(
b0000000000000001 )
1>
b1000 C
#1380
0>
#1390
1$
0(
b0000000000000010 )
1>
b0111 C
#1400
0>
#1410
0$
b00000000000000000000000000100000 %
b1001 &
1(
b0000000000000001 )
1>
b1001 C
#1420
0>
#1430
1$
0(
b0000000000000010 )
1>
b0111 C
#1440
0>
#1450
0$
b00000000000000000000000000100001 %
b1010 &
1(
b0000000000000001 )
1>
b1010 C
#1460
0>
#1470
1$
0(
b0000000000000010 )
1>
b0111 C
#1480
0>
#1490
0$
b00000000000000000000000000100010 %
b1011 &
1(
b0000000000000001 )
1>
b1011 C
#1500
0>
#1510
1$
0(
b0000000000000010 )
1>
b0111 C
#1520
0>
#1530
0$
b00000000000000000000000000100011 %
b1100 &
1(
b0000000000000001 )
1>
b1100 C
#1540
0>
#1550
1$
0(
b0000000000000010 )
1>
b0111 C
#1560
0>
#1570
0$
b00000000000000000000000000100100 %
b1101 &
1(
b0000000000000001 )
1>
b1101 C
#1580
0>
#1590
1$
0(
b0000000000000010 )
1>
b0111 C
#1600
0>
#1610
0$
b00000000000000000000000000100101 %
b1110 &
1(
b0000000000000001 )
1>
b1110 C
#1620
0>
#1630
1$
0(
b0000000000000010 )
1>
b0111 C
#1640
0>
#1650
0$
b00000000000000000000000000100110 %
b1111 &
1(
b0000000000000001 )
1>
b1111 C
#1660
0>
#1670
1$
0(
b0000000000000010 )
1>
b0111 C
#1680
0>
#1690
0$
b00000000000000000000000000100111 %
b0000 &
1(
b0000000000000001 )
1>
b0000 C
#1700
0>
#1710
1$
0(
b0000000000000010 )
1>
b0111 C
#1720
0>
#1730
0$
b00000000000000000000000000101000 %
b0001 &
1(
b0000000000000001 )
1>
b0001 C
#1740
0>
#1750
1$
0(
b0000000000000010 )
1>
b0111 C
#1760
0>
#1770
0$
b00000000000000000000000000101001 %
b0010 &
1(
b0000000000000001 )
1>
b0010 C
#1780
0>
#1790
1$
0(
b0000000000000010 )
1>
b0111 C
#1800
0>
#1810
0$
b00000000000000000000000000101010 %
b0011 &
1(
b0000000000000001 )
1>
b0011 C
#1820
0>
#1830
1$
0(
b0000000000000010 )
1>
b0111 C
#1840
0>
#1850
0$
b00000000000000000000000000101011 %
b0100 &
1(
b0000000000000001 )
1>
b0100 C
#1860
0>
#1870
1$
0(
b0000000000000010 )
1>
b0111 C
#1880
0>
#1890
0$
b00000000000000000000000000101100 %
b0101 &
1(
b0000000000000001 )
1>
b0101 C
#1900
0>
#1910
1$
0(
b0000000000000010 )
1>
b0111 C
#1920
0>
#1930
0$
b00000000000000000000000000101101 %
b0110 &
1(
b0000000000000001 )
1>
b0110 C
#1940
0>
#1950
1$
0(
b0000000000000010 )
1>
b0111 C
#1960
0>
#1970
0$
b00000000000000000000000000101110 %
b0111 &
1(
b0000000000000001 )
1>
#1980
0>
#1990
1$
0(
b0000000000000010 )
1>
#2000
0>
#2010
0$
b00000000000000000000000000101111 %
b1000 &
1(
b0000000000000001 )
1>
b1000 C
#2020
0>
#2030
1$
0(
b0000000000000010 )
1>
b0111 C
#2040
0>
#2050
0$
b00000000000000000000000000110000 %
b1001 &
1(
b0000000000000001 )
1>
b1001 C
#2060
0>
#2070
1$
0(
b0000000000000010 )
1>
b0111 C
#2080
0>
#2090
0$
b00000000000000000000000000110001 %
b1010 &
1(
b0000000000000001 )
1>
b1010 C
#2100
0>
#2110
1$
0(
b0000000000000010 )
1>
b0111 C
#2120
0>
#2130
0$
b00000000000000000000000000110010 %
b1011 &
1(
b0000000000000001 )
1>
b1011 C
#2140
0>
#2150
1$
0(
b0000000000000010 )
1>
b0111 C
#2160
0>
#2170
0$
b00000000000000000000000000110011 %
b1100 &
1(
b0000000000000001 )
1>
b1100 C
#2180
0>
#2190
1$
0(
b0000000000000010 )
1>
b0111 C
#2200
0>
#2210
0$
b00000000000000000000000000110100 %
b1101 &
1(
b0000000000000001 )
1>
b1101 C
#2220
0>
#2230
1$
0(
b0000000000000010 )
1>
b0111 C
#2240
0>
#2250
0$
b00000000000000000000000000110101 %
b1110 &
1(
b0000000000000001 )
1>
b1110 C
#2260
0>
#2270
1$
0(
b0000000000000010 )
1>
b0111 C
#2280
0>
#2290
0$
b00000000000000000000000000110110 %
b1111 &
1(
b0000000000000001 )
1>
b1111 C
#2300
0>
#2310
1$
0(
b0000000000000010 )
1>
b0111 C
#2320
0>
#2330
0$
b00000000000000000000000000110111 %
b0000 &
1(
b0000000000000001 )
1>
b0000 C
#2340
0>
#2350
1$
0(
b0000000000000010 )
1>
b0111 C
#2360
0>
#2370
0$
b00000000000000000000000000111000 %
b0001 &
1(
b0000000000000001 )
1>
b0001 C
#2380
0>
#2390
1$
0(
b0000000000000010 )
1>
b0111 C
#2400
0>
#2410
0$
b00000000000000000000000000111001 %
b0010 &
1(
b0000000000000001 )
1>
b0010 C
#2420
0>
#2430
1$
0(
b0000000000000010 )
1>
b0111 C
#2440
0>
#2450
0$
b00000000000000000000000000111010 %
b0011 &
1(
b0000000000000001 )
1>
b0011 C
#2460
0>
#2470
1$
0(
b0000000000000010 )
1>
b0111 C
#2480
0>
#2490
0$
b00000000000000000000000000111011 %
b0100 &
1(
b0000000000000001 )
1>
b0100 C
#2500
0>
#2510
1$
0(
b0000000000000010 )
1>
b0111 C
#2520
0>
#2530
0$
b00000000000000000000000000111100 %
b0101 &
1(
b0000000000000001 )
1>
b0101 C
#2540
0>
#2550
1$
0(
b0000000000000010 )
1>
b0111 C
#2560
0>
#2570
0$
b00000000000000000000000000111101 %
b0110 &
1(
b0000000000000001 )
1>
b0110 C
#2580
0>
#2590
1$
0(
b0000000000000010 )
1>
b0111 C
#2600
0>
#2610
0$
b00000000000000000000000000111110 %
b0111 &
1(
b0000000000000001 )
1>
#2620
0>
#2630
1$
0(
b0000000000000010 )
1>
#2640
0>
#2650
0$
b00000000000000000000000000111111 %
b1000 &
1(
b0000000000000001 )
1>
b1000 C
#2660
0>
#2670
1$
0(
b0000000000000010 )
1>
b0111 C
#2680
0>
#2690
0$
b00000000000000000000000001000000 %
b1001 &
1(
b0000000000000001 )
1>
b1001 C
#2700
0>
#2710
1$
0(
b0000000000000010 )
1>
b0111 C
#2720
0>
#2730
0$
b00000000000000000000000001000001 %
b1010 &
1(
b0000000000000001 )
1>
b1010 C
#2740
0>
#2750
1$
0(
b0000000000000010 )
1>
b0111 C
#2760
0>
#2770
0$
b00000000000000000000000001000010 %
b1011 &
1(
b0000000000000001 )
1>
b1011 C
#2780
0>
#2790
1$
0(
b0000000000000010 )
1>
b0111 C
#2800
0>
#2810
0$
b00000000000000000000000001000011 %
b1100 &
1(
b0000000000000001 )
1>
b1100 C
#2820
0>
#2830
1$
0(
b0000000000000010 )
1>
b0111 C
#2840
0>
#2850
0$
b00000000000000000000000001000100 %
b1101 &
1(
b0000000000000001 )
1>
b1101 C
#2860
0>
#2870
1$
0(
b0000000000000010 )
1>
b0111 C
#2880
0>
#2890
0$
b00000000000000000000000001000101 %
b1110 &
1(
b0000000000000001 )
1>
b1110 C
#2900
0>
#2910
1$
0(
b0000000000000010 )
1>
b0111 C
#2920
0>
#2930
0$
b00000000000000000000000001000110 %
b1111 &
1(
b0000000000000001 )
1>
b1111 C
#2940
0>
#2950
1$
0(
b0000000000000010 )
1>
b0111 C
#2960
0>
#2970
0$
b00000000000000000000000001000111 %
b0000 &
1(
b0000000000000001 )
1>
b0000 C
#2980
0>
#2990
1$
0(
b0000000000000010 )
1>
b0111 C
#3000
0>
#3010
0$
b00000000000000000000000001001000 %
b0001 &
1(
b0000000000000001 )
1>
b0001 C
#3020
0>
#3030
1$
0(
b0000000000000010 )
1>
b0111 C
#3040
0>
#3050
0$
b00000000000000000000000001001001 %
b0010 &
1(
b0000000000000001 )
1>
b0010 C
#3060
0>
#3070
1$
0(
b0000000000000010 )
1>
b0111 C
#3080
0>
#3090
0$
b00000000000000000000000001001010 %
b0011 &
1(
b0000000000000001 )
1>
b0011 C
#3100
0>
#3110
1$
0(
b0000000000000010 )
1>
b0111 C
#3120
0>
#3130
0$
b00000000000000000000000001001011 %
b0100 &
1(
b0000000000000001 )
1>
b0100 C
#3140
0>
#3150
1$
0(
b0000000000000010 )
1>
b0111 C
#3160
0>
#3170
0$
b00000000000000000000000001001100 %
b0101 &
1(
b0000000000000001 )
1>
b0101 C
#3180
0>
#3190
1$
0(
b0000000000000010 )
1>
b0111 C
#3200
0>
#3210
0$
b00000000000000000000000001001101 %
b0110 &
1(
b0000000000000001 )
1>
b0110 C
#3220
0>
#3230
1$
0(
b0000000000000010 )
1>
b0111 C
#3240
0>
#3250
0$
b00000000000000000000000001001110 %
b0111 &
1(
b0000000000000001 )
1>
#3260
0>
#3270
1$
0(
b0000000000000010 )
1>
#3280
0>
#3290
0$
b00000000000000000000000001001111 %
b1000 &
1(
b0000000000000001 )
1>
b1000 C
#3300
0>
#3310
1$
0(
b0000000000000010 )
1>
b0111 C
#3320
0>
#3330
0$
b00000000000000000000000001010000 %
b1001 &
1(
b0000000000000001 )
1>
b1001 C
#3340
0>
#3350
1$
0(
b0000000000000010 )
1>
b0111 C
#3360
0>
#3370
0$
b00000000000000000000000001010001 %
b1010 &
1(
b0000000000000001 )
1>
b1010 C
#3380
0>
#3390
1$
0(
b0000000000000010 )
1>
b0111 C
#3400
0>
#3410
0$
b00000000000000000000000001010010 %
b1011 &
1(
b0000000000000001 )
1>
b1011 C
#3420
0>
#3430
1$
0(
b0000000000000010 )
1>
b0111 C
#3440
0>
#3450
0$
b00000000000000000000000001010011 %
b1100 &
1(
b0000000000000001 )
1>
b1100 C
#3460
0>
#3470
1$
0(
b0000000000000010 )
1>
b0111 C
#3480
0>
#3490
0$
b00000000000000000000000001010100 %
b1101 &
1(
b0000000000000001 )
1>
b1101 C
#3500
0>
#3510
1$
0(
b0000000000000010 )
1>
b0111 C
#3520
0>
#3530
0$
b00000000000000000000000001010101 %
b1110 &
1(
b0000000000000001 )
1>
b1110 C
#3540
0>
#3550
1$
0(
b0000000000000010 )
1>
b0111 C
#3560
0>
#3570
0$
b00000000000000000000000001010110 %
b1111 &
1(
b0000000000000001 )
1>
b1111 C
#3580
0>
#3590
1$
0(
b0000000000000010 )
1>
b0111 C
#3600
0>
#3610
0$
b00000000000000000000000001010111 %
b0000 &
1(
b0000000000000001 )
1>
b0000 C
#3620
0>
#3630
1$
0(
b0000000000000010 )
1>
b0111 C
#3640
0>
#3650
0$
b00000000000000000000000001011000 %
b0001 &
1(
b0000000000000001 )
1>
b0001 C
#3660
0>
#3670
1$
0(
b0000000000000010 )
1>
b0111 C
#3680
0>
#3690
0$
b00000000000000000000000001011001 %
b0010 &
1(
b0000000000000001 )
1>
b0010 C
#3700
0>
#3710
1$
0(
b0000000000000010 )
1>
b0111 C
#3720
0>
#3730
0$
b00000000000000000000000001011010 %
b0011 &
1(
b0000000000000001 )
1>
b0011 C
#3740
0>
#3750
1$
0(
b0000000000000010 )
1>
b0111 C
#3760
0>
#3770
0$
b00000000000000000000000001011011 %
b0100 &
1(
b0000000000000001 )
1>
b0100 C
#3780
0>
#3790
1$
0(
b0000000000000010 )
1>
b0111 C
#3800
0>
#3810
0$
b00000000000000000000000001011100 %
b0101 &
1(
b0000000000000001 )
1>
b0101 C
#3820
0>
#3830
1$
0(
b0000000000000010 )
1>
b0111 C
#3840
0>
#3850
0$
b00000000000000000000000001011101 %
b0110 &
1(
b0000000000000001 )
1>
b0110 C
#3860
0>
#3870
1$
0(
b0000000000000010 )
1>
b0111 C
#3880
0>
#3890
0$
b00000000000000000000000001011110 %
b0111 &
1(
b0000000000000001 )
1>
#3900
0>
#3910
1$
0(
b0000000000000010 )
1>
#3920
0>
#3930
0$
b00000000000000000000000001011111 %
b1000 &
1(
b0000000000000001 )
1>
b1000 C
#3940
0>
#3950
1$
0(
b0000000000000010 )
1>
b0111 C
#3960
0>
#3970
0$
b00000000000000000000000001100000 %
b1001 &
1(
b0000000000000001 )
1>
b1001 C
#3980
0>
#3990
1$
0(
b0000000000000010 )
1>
b0111 C
#4000
0>
#4010
0$
b00000000000000000000000001100001 %
b1010 &
1(
b0000000000000001 )
1>
b1010 C
#4020
0>
#4030
1$
0(
b0000000000000010 )
1>
b0111 C
#4040
0>
#4050
0$
b00000000000000000000000001100010 %
b1011 &
1(
b0000000000000001 )
1>
b1011 C
#4060
0>
#4070
1$
0(
b0000000000000010 )
1>
b0111 C
#4080
0>
#4090
0$
b00000000000000000000000001100011 %
b1100 &
1(
b0000000000000001 )
1>
b1100 C
#4100
0>
#4110
1$
0(
b0000000000000010 )
1>
b0111 C
#4120
0>
#4130
0$
b00000000000000000000000001100100 %
b1101 &
1(
b0000000000000001 )
1>
b1101 C
#4140
0>
#4150
1$
0(
b0000000000000010 )
1>
b0111 C
#4160
0>
#4170
0$
b00000000000000000000000001100101 %
b1110 &
1(
b0000000000000001 )
1>
b1110 C
#4180
0>
#4190
1$
0(
b0000000000000010 )
1>
b0111 C
#4200
0>
#4210
0$
b00000000000000000000000001100110 %
b1111 &
1(
b0000000000000001 )
1>
b1111 C
#4220
0>
#4230
1$
0(
b0000000000000010 )
1>
b0111 C
#4240
0>
#4250
0$
b00000000000000000000000001100111 %
b0000 &
1(
b0000000000000001 )
1>
b0000 C
#4260
0>
#4270
1$
0(
b0000000000000010 )
1>
b0111 C
#4280
0>
#4290
0$
b00000000000000000000000001101000 %
b0001 &
1(
b0000000000000001 )
1>
b0001 C
#4300
0>
#4310
1$
0(
b0000000000000010 )
1>
b0111 C
#4320
0>
#4330
0$
b00000000000000000000000001101001 %
b0010 &
1(
b0000000000000001 )
1>
b0010 C
#4340
0>
#4350
1$
0(
b0000000000000010 )
1>
b0111 C
#4360
0>
#4370
0$
b00000000000000000000000001101010 %
b0011 &
1(
b0000000000000001 )
1>
b0011 C
#4380
0>
#4390
1$
0(
b0000000000000010 )
1>
b0111 C
#4400
0>
#4410
0$
b00000000000000000000000001101011 %
b0100 &
1(
b0000000000000001 )
1>
b0100 C
#4420
0>
#4430
1$
0(
b0000000000000010 )
1>
b0111 C
#4440
0>
#4450
0$
b00000000000000000000000001101100 %
b0101 &
1(
b0000000000000001 )
1>
b0101 C
#4460
0>
#4470
1$
0(
b0000000000000010 )
1>
b0111 C
#4480
0>
#4490
0$
b00000000000000000000000001101101 %
b0110 &
1(
b0000000000000001 )
1>
b0110 C
#4500
0>
#4510
1$
0(
b0000000000000010 )
1>
b0111 C
#4520
0>
#4530
0$
b00000000000000000000000001101110 %
b0111 &
1(
b0000000000000001 )
1>
#4540
0>
#4550
1$
0(
b0000000000000010 )
1>
#4560
0>
#4570
0$
b00000000000000000000000001101111 %
b1000 &
1(
b0000000000000001 )
1>
b1000 C
#4580
0>
#4590
1$
0(
b0000000000000010 )
1>
b0111 C
#4600
0>
#4610
0$
b00000000000000000000000001110000 %
b1001 &
1(
b0000000000000001 )
1>
b1001 C
#4620
0>
#4630
1$
0(
b0000000000000010 )
1>
b0111 C
#4640
0>
#4650
0$
b00000000000000000000000001110001 %
b1010 &
1(
b0000000000000001 )
1>
b1010 C
#4660
0>
#4670
1$
0(
b0000000000000010 )
1>
b0111 C
#4680
0>
#4690
0$
b00000000000000000000000001110010 %
b1011 &
1(
b0000000000000001 )
1>
b1011 C
#4700
0>
#4710
1$
0(
b0000000000000010 )
1>
b0111 C
#4720
0>
#4730
0$
b00000000000000000000000001110011 %
b1100 &
1(
b0000000000000001 )
1>
b1100 C
#4740
0>
#4750
1$
0(
b0000000000000010 )
1>
b0111 C
#4760
0>
#4770
0$
b00000000000000000000000001110100 %
b1101 &
1(
b0000000000000001 )
1>
b1101 C
#4780
0>
#4790
1$
0(
b0000000000000010 )
1>
b0111 C
#4800
0>
#4810
0$
b00000000000000000000000001110101 %
b1110 &
1(
b0000000000000001 )
1>
b1110 C
#4820
0>
#4830
1$
0(
b0000000000000010 )
1>
b0111 C
#4840
0>
#4850
0$
b00000000000000000000000001110110 %
b1111 &
1(
b0000000000000001 )
1>
b1111 C
#4860
0>
#4870
1$
0(
b0000000000000010 )
1>
b0111 C
#4880
0>
#4890
0$
b00000000000000000000000001110111 %
b0000 &
1(
b0000000000000001 )
1>
b0000 C
#4900
0>
#4910
1$
0(
b0000000000000010 )
1>
b0111 C
#4920
0>
#4930
0$
b00000000000000000000000001111000 %
b0001 &
1(
b0000000000000001 )
1>
b0001 C
#4940
0>
#4950
1$
0(
b0000000000000010 )
1>
b0111 C
#4960
0>
#4970
0$
b00000000000000000000000001111001 %
b0010 &
1(
b0000000000000001 )
1>
b0010 C
#4980
0>
#4990
1$
0(
b0000000000000010 )
1>
b0111 C
#5000
0>
#5010
0$
b00000000000000000000000001111010 %
b0011 &
1(
b0000000000000001 )
1>
b0011 C
#5020
0>
#5030
1$
0(
b0000000000000010 )
1>
b0111 C
#5040
0>
#5050
0$
b00000000000000000000000001111011 %
b0100 &
1(
b0000000000000001 )
1>
b0100 C
#5060
0>
#5070
1$
0(
b0000000000000010 )
1>
b0111 C
#5080
0>
#5090
0$
b00000000000000000000000001111100 %
b0101 &
1(
b0000000000000001 )
1>
b0101 C
#5100
0>
#5110
1$
0(
b0000000000000010 )
1>
b0111 C
#5120
0>
#5130
0$
b00000000000000000000000001111101 %
b0110 &
1(
b0000000000000001 )
1>
b0110 C
#5140
0>
#5150
1$
0(
b0000000000000010 )
1>
b0111 C
#5160
0>
#5170
0$
b00000000000000000000000001111110 %
b0111 &
1(
b0000000000000001 )
1>
#5180
0>
#5190
1$
0(
b0000000000000010 )
1>
#5200
0>
#5210
0$
b00000000000000000000000001111111 %
b1000 &
1(
b0000000000000001 )
1>
b1000 C
#5220
0>
#5230
1$
0(
b0000000000000010 )
1>
b0111 C
#5240
0>
#5250
0$
b00000000000000000000000010000000 %
b1001 &
1(
b0000000000000001 )
1>
b1001 C
#5260
0>
#5270
1$
0(
b0000000000000010 )
1>
b0111 C
#5280
0>
#5290
0$
b00000000000000000000000010000001 %
b1010 &
1(
b0000000000000001 )
1>
b1010 C
#5300
0>
#5310
1$
0(
b0000000000000010 )
1>
b0111 C
#5320
0>
