lab1/collatz.sv
module collatz( input logic         clk,   // Clock
		input logic 	    go,    // Load value from n; start iterating
		input logic  [31:0] n,     // Start value; only read when go = 1
		output logic [31:0] dout,  // Iteration value: true after go = 1
		output logic 	    done); // True when dout reaches 1

   /* Replace this comment and the code below with your solution */
	assign done = (!go && (dout == 32'd1));

	/* triggered by rising edge */
	always_ff @(posedge clk) begin
		// Reset the state and start the computation.
		if (go) begin
			if(n==0)
				dout <= 32'd1;
			else
				dout <= n;
		end
		// core logic of Collatz conjecture.
		else if (!done) begin
			if (dout[0] == 1'b0) begin
				dout <= dout >> 1;
			end else begin
				dout <= (dout * 3) + 1;
			end
		end
	end
   /* Replace this comment and the code above with your solution */

endmodule

lab1/ref.sv
// verilator lint_off UNUSED

module range
   #(parameter
     RAM_WORDS = 16,            // Number of counts to store in RAM
     RAM_ADDR_BITS = 4)         // Number of RAM address bits
   (input logic         clk,    // Clock
    input logic         go,     // Read start and start testing
    input logic [31:0]  start,  // Number to start from or for reading the count
    output logic        done,   // True once memory is filled
    output logic [15:0] count); // Iteration count once finished

   logic               cgo, cdone;
   logic [31:0]        n;
   logic [RAM_ADDR_BITS-1:0] num;
   logic               running;
   logic [15:0]        din;
   logic               we;
   logic [31:0]        dummy_dout; // Dummy variable for dout
   logic [15:0]        mem[RAM_WORDS-1:0]; // The RAM

   // Instantiate the Collatz iterator with dummy_dout for dout
   collatz c1(.clk(clk),
              .go(cgo),
              .n(n),
              .dout(dummy_dout),
              .done(cdone));

   // Logic for managing the iteration process and storing the results in mem
   always_ff @(posedge clk) begin
      if (go && !running) begin
         running <= 1;
         n <= start;
         num <= 0;
         din <= 0; // Start iteration count at 0
         cgo <= 1; // Pulse cgo to start collatz
         done <= 0; // Ensure done is low initially
      end else if (running) begin
         cgo <= 0; // Ensure cgo is pulsed only once per iteration
         if (cdone) begin
            we <= 1; // Enable write for a single cycle
            if (we) begin
               mem[num] <= din; // Store the iteration count
               if (num == RAM_WORDS[RAM_ADDR_BITS-1:0]-1) begin
                  running <= 0;
                  done <= 1; // Pulse done signal to indicate completion
                  we <= 0; // Disable write after storing the last value
               end else begin
                  num <= num + 1;
                  n <= n + 1; // Move to the next number
                  din <= 0; // Reset iteration count for the next number
                  cgo <= 1; // Start next Collatz iteration
               end
            end
         end else if (we) begin
            we <= 0; // Disable write after one cycle
         end else if (!cgo && !cdone) begin
            din <= din + 1; // Increment din until cdone is asserted
         end
      end
   end

   // Logic for reading from mem when done is asserted and go is not
   always_ff @(posedge clk) begin
      if (done) begin
         // Use start as the address to read from mem when done is asserted
         count <= mem[start[RAM_ADDR_BITS-1:0]]; // Correctly read from RAM
      end
   end
endmodule

lab1/range.vcd
$version Generated by VerilatedVcd $end
$timescale 1ps $end

 $scope module TOP $end
  $var wire  1 ; clk $end
  $var wire 16 ? count [15:0] $end
  $var wire  1 > done $end
  $var wire  1 < go $end
  $var wire 32 = start [31:0] $end
  $scope module range $end
   $var wire 32 A RAM_ADDR_BITS [31:0] $end
   $var wire 32 @ RAM_WORDS [31:0] $end
   $var wire  1 $ cdone $end
   $var wire  1 # cgo $end
   $var wire  1 ; clk $end
   $var wire 16 ? count [15:0] $end
   $var wire 16 ( din [15:0] $end
   $var wire  1 > done $end
   $var wire 32 * dummy_dout [31:0] $end
   $var wire  1 < go $end
   $var wire 16 + mem[0] [15:0] $end
   $var wire 16 5 mem[10] [15:0] $end
   $var wire 16 6 mem[11] [15:0] $end
   $var wire 16 7 mem[12] [15:0] $end
   $var wire 16 8 mem[13] [15:0] $end
   $var wire 16 9 mem[14] [15:0] $end
   $var wire 16 : mem[15] [15:0] $end
   $var wire 16 , mem[1] [15:0] $end
   $var wire 16 - mem[2] [15:0] $end
   $var wire 16 . mem[3] [15:0] $end
   $var wire 16 / mem[4] [15:0] $end
   $var wire 16 0 mem[5] [15:0] $end
   $var wire 16 1 mem[6] [15:0] $end
   $var wire 16 2 mem[7] [15:0] $end
   $var wire 16 3 mem[8] [15:0] $end
   $var wire 16 4 mem[9] [15:0] $end
   $var wire 32 % n [31:0] $end
   $var wire  4 & num [3:0] $end
   $var wire  1 ' running $end
   $var wire 32 = start [31:0] $end
   $var wire  1 ) we $end
   $scope module c1 $end
    $var wire  1 ; clk $end
    $var wire  1 $ done $end
    $var wire 32 * dout [31:0] $end
    $var wire  1 # go $end
    $var wire 32 % n [31:0] $end
   $upscope $end
  $upscope $end
 $upscope $end
$enddefinitions $end


#0
0#
0$
b00000000000000000000000000000000 %
b0000 &
0'
b0000000000000000 (
0)
b00000000000000000000000000000000 *
b0000000000000000 +
b0000000000000000 ,
b0000000000000000 -
b0000000000000000 .
b0000000000000000 /
b0000000000000000 0
b0000000000000000 1
b0000000000000000 2
b0000000000000000 3
b0000000000000000 4
b0000000000000000 5
b0000000000000000 6
b0000000000000000 7
b0000000000000000 8
b0000000000000000 9
b0000000000000000 :
0;
1<
b00000000000000000000000000000111 =
0>
b0000000000000000 ?
b00000000000000000000000000010000 @
b00000000000000000000000000000100 A
#10
1#
b00000000000000000000000000000111 %
1'
1;
#20
0;
#30
0#
b00000000000000000000000000000111 *
1;
#40
0;
0<
#50
b0000000000000001 (
b00000000000000000000000000010110 *
1;
#60
0;
#70
b0000000000000010 (
b00000000000000000000000000001011 *
1;
#80
0;
#90
b0000000000000011 (
b00000000000000000000000000100010 *
1;
#100
0;
#110
b0000000000000100 (
b00000000000000000000000000010001 *
1;
#120
0;
#130
b0000000000000101 (
b00000000000000000000000000110100 *
1;
#140
0;
#150
b0000000000000110 (
b00000000000000000000000000011010 *
1;
#160
0;
#170
b0000000000000111 (
b00000000000000000000000000001101 *
1;
#180
0;
#190
b0000000000001000 (
b00000000000000000000000000101000 *
1;
#200
0;
#210
b0000000000001001 (
b00000000000000000000000000010100 *
1;
#220
0;
#230
b0000000000001010 (
b00000000000000000000000000001010 *
1;
#240
0;
#250
b0000000000001011 (
b00000000000000000000000000000101 *
1;
#260
0;
#270
b0000000000001100 (
b00000000000000000000000000010000 *
1;
#280
0;
#290
b0000000000001101 (
b00000000000000000000000000001000 *
1;
#300
0;
#310
b0000000000001110 (
b00000000000000000000000000000100 *
1;
#320
0;
#330
b0000000000001111 (
b00000000000000000000000000000010 *
1;
#340
0;
#350
b0000000000010000 (
b00000000000000000000000000000001 *
1;
#360
0;
#370
1$
b0000000000010001 (
1;
#380
0;
#390
1)
1;
#400
0;
#410
1#
b00000000000000000000000000001000 %
b0001 &
b0000000000000000 (
b0000000000010001 +
1;
#420
0;
#430
b00000000000000000000000000001001 %
b0010 &
b00000000000000000000000000001000 *
1;
#440
0;
#450
0$
b00000000000000000000000000001010 %
b0011 &
b00000000000000000000000000001001 *
1;
#460
0;
#470
0#
0)
b00000000000000000000000000001010 *
1;
#480
0;
#490
b0000000000000001 (
b00000000000000000000000000000101 *
1;
#500
0;
#510
b0000000000000010 (
b00000000000000000000000000010000 *
1;
#520
0;
#530
b0000000000000011 (
b00000000000000000000000000001000 *
1;
#540
0;
#550
b0000000000000100 (
b00000000000000000000000000000100 *
1;
#560
0;
#570
b0000000000000101 (
b00000000000000000000000000000010 *
1;
#580
0;
#590
b0000000000000110 (
b00000000000000000000000000000001 *
1;
#600
0;
#610
1$
b0000000000000111 (
1;
#620
0;
#630
1)
1;
#640
0;
#650
1#
b00000000000000000000000000001011 %
b0100 &
b0000000000000000 (
b0000000000000111 .
1;
#660
0;
#670
b00000000000000000000000000001100 %
b0101 &
b00000000000000000000000000001011 *
1;
#680
0;
#690
0$
b00000000000000000000000000001101 %
b0110 &
b00000000000000000000000000001100 *
1;
#700
0;
#710
0#
0)
b00000000000000000000000000001101 *
1;
#720
0;
#730
b0000000000000001 (
b00000000000000000000000000101000 *
1;
#740
0;
#750
b0000000000000010 (
b00000000000000000000000000010100 *
1;
#760
0;
#770
b0000000000000011 (
b00000000000000000000000000001010 *
1;
#780
0;
#790
b0000000000000100 (
b00000000000000000000000000000101 *
1;
#800
0;
#810
b0000000000000101 (
b00000000000000000000000000010000 *
1;
#820
0;
#830
b0000000000000110 (
b00000000000000000000000000001000 *
1;
#840
0;
#850
b0000000000000111 (
b00000000000000000000000000000100 *
1;
#860
0;
#870
b0000000000001000 (
b00000000000000000000000000000010 *
1;
#880
0;
#890
b0000000000001001 (
b00000000000000000000000000000001 *
1;
#900
0;
#910
1$
b0000000000001010 (
1;
#920
0;
#930
1)
1;
#940
0;
#950
1#
b00000000000000000000000000001110 %
b0111 &
b0000000000000000 (
b0000000000001010 1
1;
#960
0;
#970
b00000000000000000000000000001111 %
b1000 &
b00000000000000000000000000001110 *
1;
#980
0;
#990
0$
b00000000000000000000000000010000 %
b1001 &
b00000000000000000000000000001111 *
1;
#1000
0;
#1010
0#
0)
b00000000000000000000000000010000 *
1;
#1020
0;
#1030
b0000000000000001 (
b00000000000000000000000000001000 *
1;
#1040
0;
#1050
b0000000000000010 (
b00000000000000000000000000000100 *
1;
#1060
0;
#1070
b0000000000000011 (
b00000000000000000000000000000010 *
1;
#1080
0;
#1090
b0000000000000100 (
b00000000000000000000000000000001 *
1;
#1100
0;
#1110
1$
b0000000000000101 (
1;
#1120
0;
#1130
1)
1;
#1140
0;
#1150
1#
b00000000000000000000000000010001 %
b1010 &
b0000000000000000 (
b0000000000000101 4
1;
#1160
0;
#1170
b00000000000000000000000000010010 %
b1011 &
b00000000000000000000000000010001 *
1;
#1180
0;
#1190
0$
b00000000000000000000000000010011 %
b1100 &
b00000000000000000000000000010010 *
1;
#1200
0;
#1210
0#
0)
b00000000000000000000000000010011 *
1;
#1220
0;
#1230
b0000000000000001 (
b00000000000000000000000000111010 *
1;
#1240
0;
#1250
b0000000000000010 (
b00000000000000000000000000011101 *
1;
#1260
0;
#1270
b0000000000000011 (
b00000000000000000000000001011000 *
1;
#1280
0;
#1290
b0000000000000100 (
b00000000000000000000000000101100 *
1;
#1300
0;
#1310
b0000000000000101 (
b00000000000000000000000000010110 *
1;
#1320
0;
#1330
b0000000000000110 (
b00000000000000000000000000001011 *
1;
#1340
0;
#1350
b0000000000000111 (
b00000000000000000000000000100010 *
1;
#1360
0;
#1370
b0000000000001000 (
b00000000000000000000000000010001 *
1;
#1380
0;
#1390
b0000000000001001 (
b00000000000000000000000000110100 *
1;
#1400
0;
#1410
b0000000000001010 (
b00000000000000000000000000011010 *
1;
#1420
0;
#1430
b0000000000001011 (
b00000000000000000000000000001101 *
1;
#1440
0;
#1450
b0000000000001100 (
b00000000000000000000000000101000 *
1;
#1460
0;
#1470
b0000000000001101 (
b00000000000000000000000000010100 *
1;
#1480
0;
#1490
b0000000000001110 (
b00000000000000000000000000001010 *
1;
#1500
0;
#1510
b0000000000001111 (
b00000000000000000000000000000101 *
1;
#1520
0;
#1530
b0000000000010000 (
b00000000000000000000000000010000 *
1;
#1540
0;
#1550
b0000000000010001 (
b00000000000000000000000000001000 *
1;
#1560
0;
#1570
b0000000000010010 (
b00000000000000000000000000000100 *
1;
#1580
0;
#1590
b0000000000010011 (
b00000000000000000000000000000010 *
1;
#1600
0;
#1610
b0000000000010100 (
b00000000000000000000000000000001 *
1;
#1620
0;
#1630
1$
b0000000000010101 (
1;
#1640
0;
#1650
1)
1;
#1660
0;
#1670
1#
b00000000000000000000000000010100 %
b1101 &
b0000000000000000 (
b0000000000010101 7
1;
#1680
0;
#1690
b00000000000000000000000000010101 %
b1110 &
b00000000000000000000000000010100 *
1;
#1700
0;
#1710
0$
b00000000000000000000000000010110 %
b1111 &
b00000000000000000000000000010101 *
1;
#1720
0;
#1730
0#
0)
b00000000000000000000000000010110 *
1;
#1740
0;
#1750
b0000000000000001 (
b00000000000000000000000000001011 *
1;
#1760
0;
#1770
b0000000000000010 (
b00000000000000000000000000100010 *
1;
#1780
0;
#1790
b0000000000000011 (
b00000000000000000000000000010001 *
1;
#1800
0;
#1810
b0000000000000100 (
b00000000000000000000000000110100 *
1;
#1820
0;
#1830
b0000000000000101 (
b00000000000000000000000000011010 *
1;
#1840
0;
#1850
b0000000000000110 (
b00000000000000000000000000001101 *
1;
#1860
0;
#1870
b0000000000000111 (
b00000000000000000000000000101000 *
1;
#1880
0;
#1890
b0000000000001000 (
b00000000000000000000000000010100 *
1;
#1900
0;
#1910
b0000000000001001 (
b00000000000000000000000000001010 *
1;
#1920
0;
#1930
b0000000000001010 (
b00000000000000000000000000000101 *
1;
#1940
0;
#1950
b0000000000001011 (
b00000000000000000000000000010000 *
1;
#1960
0;
#1970
b0000000000001100 (
b00000000000000000000000000001000 *
1;
#1980
0;
#1990
b0000000000001101 (
b00000000000000000000000000000100 *
1;
#2000
0;
#2010
b0000000000001110 (
b00000000000000000000000000000010 *
1;
#2020
0;
#2030
b0000000000001111 (
b00000000000000000000000000000001 *
1;
#2040
0;
#2050
1$
b0000000000010000 (
1;
#2060
0;
#2070
1)
1;
#2080
0;
#2090
0'
0)
b0000000000010000 :
1;
1>
#2100
0;
b00000000000000000000000000000000 =
#2110
1;
b0000000000010001 ?
#2120
0;
b00000000000000000000000000000001 =
#2130
1;
b0000000000000000 ?
#2140
0;
b00000000000000000000000000000010 =
#2150
1;
#2160
0;
b00000000000000000000000000000011 =
#2170
1;
b0000000000000111 ?
#2180
0;
b00000000000000000000000000000100 =
#2190
1;
b0000000000000000 ?
#2200
0;
b00000000000000000000000000000101 =
#2210
1;
#2220
0;
b00000000000000000000000000000110 =
#2230
1;
b0000000000001010 ?
#2240
0;
b00000000000000000000000000000111 =
#2250
1;
b0000000000000000 ?
#2260
0;
b00000000000000000000000000001000 =
#2270
1;
#2280
0;
b00000000000000000000000000001001 =
#2290
1;
b0000000000000101 ?
#2300
0;
b00000000000000000000000000001010 =
#2310
1;
b0000000000000000 ?
#2320
0;
b00000000000000000000000000001011 =
#2330
1;
#2340
0;
b00000000000000000000000000001100 =
#2350
1;
b0000000000010101 ?
#2360
0;
b00000000000000000000000000001101 =
#2370
1;
b0000000000000000 ?
#2380
0;
b00000000000000000000000000001110 =
#2390
1;
#2400
0;
b00000000000000000000000000001111 =
#2410
1;
b0000000000010000 ?
